Workbook

Sheet Resumen
B2: Mi Catorcena
B3: Resumen financiero personal
B5: Ingreso catorcenal | C5: =Gastos!C5 -> 6000 | E5: % ingreso usado en gastos fijos | F5: =C6/C5 -> 0.61533333
B6: Gastos fijos (catorcenal) | C6: =Gastos!C13 -> 3692 | E6: Estado del semáforo | F6: =IF(F5<0.6,"Vas bien",IF(F5<0.85,"Cuidado","Alerta")) -> Cuidado
B7: Libre disponible (catorcenal) | C7: =Gastos!C14 -> 2308
B8: Deuda total pendiente | C8: =Deudas!E10 -> 7191
B10: Ingreso mensual | C10: =C5*2 -> 12000
B11: Gastos fijos mensuales | C11: =C6*2 -> 7384
B12: Libre mensual | C12: =C7*2 -> 4616
B13: Ahorro acumulado | C13: =Ahorro!D25 -> 0
B16: Concepto | C16: Monto
B17: Escuela | C17: =Gastos!C8 -> 1512
B18: Renta | C18: =Gastos!C9 -> 1000
B19: Comida | C19: =Gastos!C11 -> 600
B20: Internet | C20: =Gastos!C12 -> 230
B21: Libre | C21: =C7 -> 2308

Sheet Gastos
B2: Ingreso y gastos fijos
B3: Edita solo las celdas en azul — todo lo demás se calcula solo
B5: Ingreso catorcenal | C5: 6000
B7: Gasto | C7: Monto catorcenal
B8: Escuela | C8: 1512
B9: Renta | C9: 1000
B10: Vacunas gatos | C10: 350
B11: Comida | C11: 600
B12: Internet (mensual / 2) | C12: 230
B13: Total gastos fijos | C13: =SUM(C8:C12) -> 3692
B14: Libre disponible (catorcenal) | C14: =C5-C13 -> 2308
B17: Nota: si tu internet es mensual, ya viene dividido entre 2 catorcenas.

Sheet Deudas
B2: Seguimiento de deudas
B3: Registra tus abonos en la columna Pagado
B5: Deuda | C5: Monto | D5: Pagado | E5: Restante | F5: % Pagado
B6: Boleto Karol G | C6: 2000 | D6: 0 | E6: =C6-D6 -> 2000 | F6: =D6/C6 -> 0
B7: Préstamo papá | C7: 500 | E7: =C7-D7 -> 500 | F7: =D7/C7 -> 0
B8: Ropa Suburbia | C8: 3791 | D8: 1100 | E8: =C8-D8 -> 2691 | F8: =D8/C8 -> 0.29016091
B9: Bolso | C9: 2000 | D9: 0 | E9: =C9-D9 -> 2000 | F9: =D9/C9 -> 0
B10: Total | C10: =SUM(C6:C9) -> 8291 | D10: =SUM(D6:D9) -> 1100 | E10: =SUM(E6:E9) -> 7191
B13: Plan de pago sugerido
B14: Libre catorcenal disponible | C14: =Gastos!C14 -> 2308
B15: Catorcenas para liquidar (si destinas todo tu libre) | C15: =IF(C14<=0,"-",ROUNDUP(Deudas!E10/C14,0)) -> 4

Sheet Ahorro
B2: Control de ahorro
B3: Agrega una fila por cada catorcena que ahorres
B5: Fecha | C5: Monto ahorrado | D5: Acumulado
D6: =SUM($C$6:C6) -> 0
D7: =SUM($C$6:C7) -> 0
D8: =SUM($C$6:C8) -> 0
D9: =SUM($C$6:C9) -> 0
D10: =SUM($C$6:C10) -> 0
D11: =SUM($C$6:C11) -> 0
D12: =SUM($C$6:C12) -> 0
D13: =SUM($C$6:C13) -> 0
D14: =SUM($C$6:C14) -> 0
D15: =SUM($C$6:C15) -> 0
D16: =SUM($C$6:C16) -> 0
D17: =SUM($C$6:C17) -> 0
... D25: =SUM($C$6:C25) -> 0

Sheet Calendario
B2: Calendario de pagos
B3: Tus pagos recurrentes, jalados directo de la hoja Gastos y Deudas
B5: Cuándo | C5: Concepto | D5: Monto
B6: Día de pago | C6: Depósito de sueldo catorcenal | D6: =Gastos!C5 -> 6000
B7: 2 días después del pago | C7: Escuela | D7: =Gastos!C8 -> 1512
B8: Cada catorcena | C8: Renta | D8: =Gastos!C9 -> 1000
B9: Cada catorcena | C9: Comida | D9: =Gastos!C11 -> 600
B10: 1 vez al mes | C10: Internet (monto mensual) | D10: =Gastos!C12*2 -> 460
B11: Pendiente | C11: Deuda: Boleto Karol G | D11: =Deudas!E6 -> 2000
B12: Pendiente | C12: Deuda: Ropa Suburbia | D12: 3791
B13: Pendiente | C13: Deuda: Bolso | D13: =Deudas!E9 -> 2000
